koogu/__init__.py
koogu/inference.py
koogu/train_and_eval.py
koogu/data/__init__.py
koogu/data/augmentations.py
koogu/data/feeder.py
koogu/data/preprocess.py
koogu/data/raw.py
koogu/data/tf_transformations.py
koogu/data/annotations/__init__.py
koogu/data/annotations/audacity.py
koogu/data/annotations/raven.py
koogu/data/annotations/sonicvisualiser.py
koogu/model/__init__.py
koogu/model/trained_model.py
koogu/model/architectures/__init__.py
koogu/model/architectures/convnet.py
koogu/model/architectures/densenet.py
koogu/utils/__init__.py
koogu/utils/assessments.py
koogu/utils/config.py
koogu/utils/detections.py
koogu/utils/filesystem.py
koogu/utils/terminal.py
koogu-0.7.2.dist-info/LICENSE
koogu-0.7.2.dist-info/METADATA
koogu-0.7.2.dist-info/WHEEL
koogu-0.7.2.dist-info/top_level.txt
koogu-0.7.2.dist-info/RECORD
