Metadata-Version: 2.1
Name: koogu
Version: 0.7.2
Summary: Machine Learning for Bioacoustics
Home-page: https://shyamblast.github.io/Koogu/
Author: Shyam Madhusudhana
Author-email: shyam.m@curtin.edu.au
License: GNU General Public License v3.0
Classifier: Programming Language :: Python
Classifier: Programming Language :: Python :: 3
Classifier: License :: OSI Approved :: GNU General Public License v3 (GPLv3)
Classifier: Intended Audience :: Science/Research
Classifier: Topic :: Scientific/Engineering
Classifier: Topic :: Multimedia :: Sound/Audio :: Analysis
Requires-Python: >=3.7
License-File: LICENSE
Requires-Dist: numpy
Requires-Dist: scipy
Requires-Dist: soundfile
Requires-Dist: audioread
Requires-Dist: resampy
Requires-Dist: tensorflow (>=2.7)
